nbdev_pascal_fr/__init__.py
nbdev_pascal_fr/accel.py
nbdev_pascal_fr/activations.py
nbdev_pascal_fr/augment.py
nbdev_pascal_fr/conv.py
nbdev_pascal_fr/core.py
nbdev_pascal_fr/datasets.py
nbdev_pascal_fr/diffusion.py
nbdev_pascal_fr/fid.py
nbdev_pascal_fr/init.py
nbdev_pascal_fr/learner.py
nbdev_pascal_fr/pascalito.py
nbdev_pascal_fr/resnet.py
nbdev_pascal_fr/sgd.py
nbdev_pascal_fr/training.py
nbdev_pascal_fr-0.0.3.dist-info/LICENSE
nbdev_pascal_fr-0.0.3.dist-info/METADATA
nbdev_pascal_fr-0.0.3.dist-info/WHEEL
nbdev_pascal_fr-0.0.3.dist-info/entry_points.txt
nbdev_pascal_fr-0.0.3.dist-info/top_level.txt
nbdev_pascal_fr-0.0.3.dist-info/RECORD
